pyflowdiagnostics/__init__.py
pyflowdiagnostics/__main__.py
pyflowdiagnostics/flow_diagnostics.py
pyflowdiagnostics/grid.py
pyflowdiagnostics/utils.py
pyflowdiagnostics/version.py
pyflowdiagnostics/well.py
pyflowdiagnostics/readers/__init__.py
pyflowdiagnostics/readers/cmg_bin_reader.py
pyflowdiagnostics/readers/ecl_bin_reader.py
pyflowdiagnostics/readers/sr3_reader.py
pyflowdiagnostics-0.2.1.dist-info/licenses/LICENSE
pyflowdiagnostics-0.2.1.dist-info/METADATA
pyflowdiagnostics-0.2.1.dist-info/WHEEL
pyflowdiagnostics-0.2.1.dist-info/entry_points.txt
pyflowdiagnostics-0.2.1.dist-info/top_level.txt
pyflowdiagnostics-0.2.1.dist-info/RECORD
