Metadata-Version: 2.4
Name: pyflowdiagnostics
Version: 0.2.1
Summary: Flow Diagnostics Toolkit
Author-email: Tsubasa Onishi <onishi.tsubasa@eaps.ethz.ch>
License: 
Project-URL: Homepage, https://github.com/GEG-ETHZ/pyflowdiagnostics
Project-URL: Documentation, https://github.com/GEG-ETHZ/pyflowdiagnostics
Project-URL: Repository, https://github.com/GEG-ETHZ/pyflowdiagnostics
Classifier: Development Status :: 4 - Beta
Classifier: License :: OSI Approved :: Apache Software License
Classifier: Programming Language :: Python
Requires-Python: >=3.10
License-File: LICENSE
Requires-Dist: numpy
Requires-Dist: scipy
Requires-Dist: pandas
Requires-Dist: h5py
Requires-Dist: pymatsolver
Requires-Dist: xlsxwriter
Requires-Dist: scooby
Provides-Extra: docs
Requires-Dist: sphinx; extra == "docs"
Requires-Dist: sphinx_automodapi; extra == "docs"
Requires-Dist: pydata_sphinx_theme; extra == "docs"
Provides-Extra: tests
Requires-Dist: ruff; extra == "tests"
Requires-Dist: pytest; extra == "tests"
Requires-Dist: pooch; extra == "tests"
Requires-Dist: coveralls; extra == "tests"
Requires-Dist: pytest_cov; extra == "tests"
Requires-Dist: pytest-console-scripts; extra == "tests"
Provides-Extra: all
Requires-Dist: pyflowdiagnostics[docs]; extra == "all"
Requires-Dist: pyflowdiagnostics[tests]; extra == "all"
Provides-Extra: build
Requires-Dist: setuptools_scm>=8; extra == "build"
Requires-Dist: setuptools>=64; extra == "build"
Dynamic: license-file
